mdree/__init__.py
mdree/mdree.py
mdree-0.4.dist-info/LICENSE
mdree-0.4.dist-info/METADATA
mdree-0.4.dist-info/WHEEL
mdree-0.4.dist-info/top_level.txt
mdree-0.4.dist-info/zip-safe
mdree-0.4.dist-info/RECORD
